{ "type": "FeatureCollection", "crs": { "type": "name", "properties": { "name": "urn:ogc:def:crs:OGC:1.3:CRS84" } }, "features": [ 
{ "type": "Feature", "properties": { "Name": "William Falk-Wallace", "Description": "Mon Oct 14 16:54:46 EDT 2013; Location Accuracy: 65.000000" }, "geometry": { "type": "Point", "coordinates": [ -73.959827, 40.809060, 0.0 ] } },
{ "type": "Feature", "properties": { "Name": "William Falk-Wallace", "Description": "Tue Oct  8 09:13:41 EDT 2013; Location Accuracy: 164.904826" }, "geometry": { "type": "Point", "coordinates": [ -73.962577, 40.809815, 0.0 ] } }
]}
